mckit_nuclides/__init__.py
mckit_nuclides/abundance.py
mckit_nuclides/constants.py
mckit_nuclides/data/elements.parquet
mckit_nuclides/data/nuclides.parquet
mckit_nuclides/elements.py
mckit_nuclides/nuclides.py
mckit_nuclides/py.typed
mckit_nuclides-0.6.0.dist-info/WHEEL
mckit_nuclides-0.6.0.dist-info/METADATA
mckit_nuclides-0.6.0.dist-info/RECORD
