Metadata-Version: 2.3
Name: mckit-nuclides
Version: 0.6.0
Summary: Python tools to work with elements and nuclides
Keywords: abundance,element,nuclide
Author: dvp2015
Author-email: dvp2015 <dmitri_portnov@yahoo.com>
License: MIT
Classifier: Development Status :: 4 - Beta
Classifier: Environment :: Console
Classifier: Intended Audience :: Developers
Classifier: Intended Audience :: Science/Research
Classifier: Operating System :: OS Independent
Classifier: Programming Language :: Python :: 3 :: Only
Classifier: Programming Language :: Python :: 3.12
Classifier: Programming Language :: Python :: 3.13
Classifier: Programming Language :: Python :: 3.14
Classifier: Topic :: Scientific/Engineering :: Physics
Requires-Dist: numpy>=2.4
Requires-Dist: polars[all]>=1.37
Requires-Python: >=3.12, <3.15
Project-URL: Bug Tracker, https://github.com/MC-kit/mckit-nuclides/issues
Project-URL: Changelog, https://github.com/MC-kit/mckit-nuclides/releases
Project-URL: documentation, https://mckit-nuclides.readthedocs.io
Project-URL: homepage, https://github.com/MC-kit/mckit-nuclides
Project-URL: repository, https://github.com/MC-kit/mckit-nuclides
